jinja_markdown/__init__.py
jinja_markdown-1.210911.dist-info/METADATA
jinja_markdown-1.210911.dist-info/MIT-LICENSE
jinja_markdown-1.210911.dist-info/WHEEL
jinja_markdown-1.210911.dist-info/top_level.txt
jinja_markdown-1.210911.dist-info/RECORD
