Metadata-Version: 2.1
Name: jinja-markdown
Version: 1.210911
Summary: A jinja2 markdown tag powered with PyMdown Extensions.
Home-page: https://github.com/jpsca/jinja-markdown
Author: Juan-Pablo Scaletti
Author-email: juanpablo@jpscaletti.com
License: MIT
Platform: UNKNOWN
Classifier: Development Status :: 4 - Beta
Requires-Python: <4.0,>=3.6
Requires-Dist: Jinja2 (>=2.11)
Requires-Dist: Pygments (>=2.6.1)
Requires-Dist: pymdown-extensions (>=7.1)
Provides-Extra: dev
Requires-Dist: pre-commit ; extra == 'dev'
Requires-Dist: tox ; extra == 'dev'
Provides-Extra: test
Requires-Dist: pytest ; extra == 'test'
Requires-Dist: flake8 ; extra == 'test'
Requires-Dist: flake8-bugbear ; extra == 'test'
Requires-Dist: flake8-import-order ; extra == 'test'
Requires-Dist: flake8-logging-format ; extra == 'test'
Requires-Dist: flake8-quotes ; extra == 'test'
